{
  "resourceType": "StructureDefinition",
  "id": "TNMPnKategorie",
  "url": "http://idg-rlp.de/fhir/tumorkonferenzen/StructureDefinition/TNMPnKategorie",
  "name": "TNMPnKategorie",
  "title": "TNMPnKategorie",
  "status": "draft",
  "description": "TNMPnKategorie",
  "fhirVersion": "4.0.1",
  "kind": "resource",
  "abstract": false,
  "type": "Observation",
  "baseDefinition": "http://hl7.org/fhir/StructureDefinition/Observation",
  "derivation": "constraint",
  "differential": {
    "element": [
      {
        "id": "Observation.status",
        "path": "Observation.status",
        "mustSupport": true
      },
      {
        "id": "Observation.code",
        "path": "Observation.code",
        "patternCodeableConcept": {
          "coding": [
            {
              "code": "92837-4",
              "system": "http://loinc.org"
            }
          ]
        },
        "mustSupport": true
      },
      {
        "id": "Observation.subject",
        "path": "Observation.subject",
        "min": 1,
        "type": [
          {
            "code": "Reference",
            "targetProfile": [
              "http://idg-rlp.de/fhir/tumorkonferenzen/StructureDefinition/TumorPatient"
            ]
          }
        ],
        "mustSupport": true
      },
      {
        "id": "Observation.encounter",
        "path": "Observation.encounter",
        "type": [
          {
            "code": "Reference",
            "targetProfile": [
              "http://idg-rlp.de/fhir/tumorkonferenzen/StructureDefinition/verlauf"
            ]
          }
        ],
        "mustSupport": true
      },
      {
        "id": "Observation.effective[x]",
        "path": "Observation.effective[x]",
        "type": [
          {
            "code": "dateTime"
          }
        ],
        "mustSupport": true
      },
      {
        "id": "Observation.value[x]",
        "path": "Observation.value[x]",
        "type": [
          {
            "code": "CodeableConcept"
          }
        ],
        "mustSupport": true,
        "binding": {
          "strength": "required",
          "valueSet": "http://idg-rlp.de/fhir/tumorkonferenzen/ValueSet/perineurale-invasion-vs"
        }
      }
    ]
  }
}
